{
  "AXP": 4,
  "HII": 4,
  "MSI": 4,
  "NDAQ": 4,
  "V": 4,
  "BRO": 4,
  "BEN": 4,
  "AJG": 4,
  "RJF": 4,
  "COF": 4,
  "WTW": 4,
  "MRK": 4,
  "ABT": 4,
  "EFX": 4,
  "DFS": 4,
  "INCY": 1,
  "PPG": 1,
  "PM": 1,
  "HRL": 1,
  "DE": 1,
  "WMB": 1,
  "T": 1,
  "CAT": 1,
  "STZ": 1,
  "FSLR": 1,
  "VLO": 1,
  "WST": 1,
  "BWA": 1,
  "CVX": 1,
  "K": 1,
  "IFF": 1,
  "MO": 1,
  "IP": 1,
  "PKG": 1,
  "SHW": 1,
  "ADM": 1,
  "GIS": 1,
  "CLX": 1,
  "AES": 1,
  "EMN": 1,
  "EQT": 1,
  "FCX": 9,
  "EA": 9,
  "ALB": 9,
  "CE": 9,
  "BKR": 9,
  "VTRS": 9,
  "DHI": 3,
  "PNC": 3,
  "WRB": 3,
  "PGR": 3,
  "HIG": 3,
  "PHM": 3,
  "TSN": 3,
  "C": 3,
  "PFG": 3,
  "ICE": 3,
  "RF": 3,
  "CME": 3,
  "USB": 3,
  "ALL": 3,
  "BK": 3,
  "AMP": 3,
  "LEN": 3,
  "CSGP": 0,
  "DPZ": 0,
  "NFLX": 0,
  "DIS": 0,
  "AMZN": 0,
  "KMX": 0,
  "CMCSA": 0,
  "BSX": 0,
  "TDG": 0,
  "FAST": 0,
  "MSFT": 0,
  "BAX": 0,
  "SBUX": 0,
  "GOOG": 0,
  "DG": 0,
  "IRM": 0,
  "ORCL": 0,
  "EXPE": 0,
  "XYL": 0,
  "PAYX": 0,
  "MCD": 0,
  "CSCO": 0,
  "JCI": 0,
  "OMC": 0,
  "TJX": 0,
  "RTX": 0,
  "EL": 0,
  "PEP": 0,
  "AXON": 2,
  "IEX": 2,
  "TT": 2,
  "LKQ": 2,
  "BLDR": 2,
  "PWR": 2,
  "MTD": 2,
  "EQIX": 2,
  "SWK": 2,
  "ISRG": 2,
  "PH": 2,
  "RVTY": 2,
  "FDS": 2,
  "AOS": 2,
  "GPN": 2,
  "VRSK": 2,
  "TSLA": 2,
  "TTWO": 2,
  "WDC": 2,
  "DOV": 2,
  "ANSS": 2,
  "FTNT": 6,
  "NVDA": 6,
  "FFIV": 6,
  "APH": 6,
  "ON": 6,
  "GLW": 6,
  "CRM": 6,
  "LRCX": 6,
  "NTAP": 6,
  "WELL": 5,
  "FRT": 5,
  "O": 5,
  "UDR": 5,
  "DLR": 5,
  "PARA": 5,
  "HST": 5,
  "EQR": 5,
  "PODD": 5,
  "KIM": 5,
  "BBY": 5,
  "ESS": 5,
  "BDX": 8,
  "HSIC": 8,
  "HCA": 8,
  "VRTX": 8,
  "UHS": 8,
  "LH": 8,
  "DXCM": 8,
  "UPS": 10,
  "UAL": 10,
  "FDX": 10,
  "JBHT": 10,
  "CCL": 10,
  "DTE": 7,
  "ED": 7,
  "PPL": 7,
  "PNW": 7,
  "SO": 7,
  "WEC": 7,
  "EIX": 7,
  "PEG": 7
}